emmett_core-1.3.10.dist-info/METADATA
emmett_core-1.3.10.dist-info/WHEEL
emmett_core-1.3.10.dist-info/licenses/LICENSE
emmett_core/__init__.py
emmett_core/_emmett_core.cpython-39-darwin.so
emmett_core/_emmett_core.pyi
emmett_core/_imports.py
emmett_core/_internal.py
emmett_core/_io.py
emmett_core/app.py
emmett_core/cache/__init__.py
emmett_core/cache/handlers.py
emmett_core/cache/hash.py
emmett_core/cache/helpers.py
emmett_core/cryptography/__init__.py
emmett_core/cryptography/ciphers.py
emmett_core/cryptography/kdf.py
emmett_core/cryptography/symmetric.py
emmett_core/cryptography/utils.py
emmett_core/ctx.py
emmett_core/datastructures.py
emmett_core/extensions.py
emmett_core/html.py
emmett_core/http/__init__.py
emmett_core/http/headers.py
emmett_core/http/helpers.py
emmett_core/http/response.py
emmett_core/http/wrappers/__init__.py
emmett_core/http/wrappers/helpers.py
emmett_core/http/wrappers/request.py
emmett_core/http/wrappers/response.py
emmett_core/http/wrappers/websocket.py
emmett_core/log.py
emmett_core/parsers.py
emmett_core/pipeline/__init__.py
emmett_core/pipeline/dyn.py
emmett_core/pipeline/extras.py
emmett_core/pipeline/pipe.py
emmett_core/pipeline/wrappers.py
emmett_core/protocols/__init__.py
emmett_core/protocols/asgi/__init__.py
emmett_core/protocols/asgi/handlers.py
emmett_core/protocols/asgi/helpers.py
emmett_core/protocols/asgi/typing.py
emmett_core/protocols/asgi/wrappers.py
emmett_core/protocols/rsgi/__init__.py
emmett_core/protocols/rsgi/handlers.py
emmett_core/protocols/rsgi/helpers.py
emmett_core/protocols/rsgi/test_client/__init__.py
emmett_core/protocols/rsgi/test_client/_shortcuts.py
emmett_core/protocols/rsgi/test_client/client.py
emmett_core/protocols/rsgi/test_client/helpers.py
emmett_core/protocols/rsgi/test_client/scope.py
emmett_core/protocols/rsgi/test_client/urls.py
emmett_core/protocols/rsgi/wrappers.py
emmett_core/py.typed
emmett_core/routing/__init__.py
emmett_core/routing/cache.py
emmett_core/routing/dispatchers.py
emmett_core/routing/response.py
emmett_core/routing/router.py
emmett_core/routing/routes.py
emmett_core/routing/rules.py
emmett_core-1.3.10.dist-info/RECORD
